bench_sdk/__init__.py
bench_sdk/cli.py
bench_sdk-0.0.1.dist-info/licenses/LICENSE
bench_sdk-0.0.1.dist-info/METADATA
bench_sdk-0.0.1.dist-info/WHEEL
bench_sdk-0.0.1.dist-info/entry_points.txt
bench_sdk-0.0.1.dist-info/top_level.txt
bench_sdk-0.0.1.dist-info/RECORD
