Metadata-Version: 2.4
Name: bench-sdk
Version: 0.0.1
Summary: 🛠️ The SDK for building AI-powered engineering automation
Home-page: https://getbench.ai
Author: Raihaan Usman
Author-email: raihaan@getbench.ai
Project-URL: Homepage, https://getbench.ai
Project-URL: Source, https://github.com/bench-tools
Project-URL: Documentation, https://docs.getbench.ai
Keywords: SDK engineering automation AI API framework CAD CAE workflow
Classifier: Development Status :: 1 - Planning
Classifier: Intended Audience :: Developers
Classifier: Intended Audience :: Manufacturing
Classifier: Topic :: Software Development :: Libraries :: Python Modules
Classifier: Topic :: Scientific/Engineering :: Artificial Intelligence
Classifier: Topic :: Software Development :: Libraries :: Application Frameworks
Classifier: License :: OSI Approved :: MIT License
Classifier: Programming Language :: Python :: 3
Classifier: Programming Language :: Python :: 3.8
Classifier: Programming Language :: Python :: 3.9
Classifier: Programming Language :: Python :: 3.10
Classifier: Programming Language :: Python :: 3.11
Classifier: Programming Language :: Python :: 3.12
Classifier: Operating System :: OS Independent
Requires-Python: >=3.8
License-File: LICENSE
Dynamic: author
Dynamic: author-email
Dynamic: classifier
Dynamic: description
Dynamic: description-content-type
Dynamic: home-page
Dynamic: keywords
Dynamic: license-file
Dynamic: project-url
Dynamic: requires-python
Dynamic: summary
